PerfectoLibrary/__init__.py
PerfectoLibrary/version.py
PerfectoLibrary/keywords/__init__.py
PerfectoLibrary/keywords/_devices.py
PerfectoLibrary/keywords/_general.py
PerfectoLibrary/keywords/_rest_acts.py
PerfectoLibrary/keywords/keywordgroup.py
PerfectoLibrary/listeners/__init__.py
PerfectoLibrary/listeners/_perfectoListener.py
PerfectoLibrary/listeners/data/excluded_reporting_keywords.json
PerfectoLibrary/listeners/data/failure_reasons.json
perfectolibrary_py3-0.6.5.data/data/excluded_reporting_keywords.json
perfectolibrary_py3-0.6.5.data/data/failure_reasons.json
perfectolibrary_py3-0.6.5.dist-info/METADATA
perfectolibrary_py3-0.6.5.dist-info/WHEEL
perfectolibrary_py3-0.6.5.dist-info/top_level.txt
perfectolibrary_py3-0.6.5.dist-info/RECORD
